odoo8_addon_l10n_ca_toponyms-8.0.1.0.0-py2.7-nspkg.pth
odoo8_addon_l10n_ca_toponyms-8.0.1.0.0.dist-info/top_level.txt
odoo8_addon_l10n_ca_toponyms-8.0.1.0.0.dist-info/WHEEL
odoo8_addon_l10n_ca_toponyms-8.0.1.0.0.dist-info/RECORD
odoo8_addon_l10n_ca_toponyms-8.0.1.0.0.dist-info/metadata.json
odoo8_addon_l10n_ca_toponyms-8.0.1.0.0.dist-info/DESCRIPTION.rst
odoo8_addon_l10n_ca_toponyms-8.0.1.0.0.dist-info/METADATA
odoo8_addon_l10n_ca_toponyms-8.0.1.0.0.dist-info/namespace_packages.txt
odoo_addons/l10n_ca_toponyms/__openerp__.py
odoo_addons/l10n_ca_toponyms/__init__.py
odoo_addons/l10n_ca_toponyms/l10n_ca_toponyms.xml
odoo_addons/l10n_ca_toponyms/static/description/icon.png
